{
    "profiles": [
        {
            "complex_modifications": {
                "rules": [
                    {
                        "description": "Map Custom Fn Key",
                        "manipulators": [
                            {
                                "from": { "consumer_key_code": 47 },
                                "to": [{ "key_code": "fn" }],
                                "type": "basic"
                            }
                        ]
                    }
                ]
            },
            "devices": [
                {
                    "identifiers": {
                        "is_keyboard": true,
                        "product_id": 641,
                        "vendor_id": 1452
                    },
                    "simple_modifications": [
                        {
                            "from": { "key_code": "caps_lock" },
                            "to": [{ "key_code": "escape" }]
                        },
                        {
                            "from": { "key_code": "escape" },
                            "to": [{ "key_code": "caps_lock" }]
                        }
                    ]
                },
                {
                    "fn_function_keys": [
                        {
                            "from": { "key_code": "f1" },
                            "to": [{ "consumer_key_code": "al_consumer_control_configuration" }]
                        },
                        {
                            "from": { "key_code": "f2" },
                            "to": [{ "consumer_key_code": "volume_decrement" }]
                        },
                        {
                            "from": { "key_code": "f3" },
                            "to": [{ "consumer_key_code": "volume_increment" }]
                        },
                        {
                            "from": { "key_code": "f4" },
                            "to": [{ "consumer_key_code": "mute" }]
                        },
                        {
                            "from": { "key_code": "f5" },
                            "to": [{ "consumer_key_code": "rewind" }]
                        },
                        {
                            "from": { "key_code": "f6" },
                            "to": [{ "consumer_key_code": "fast_forward" }]
                        },
                        {
                            "from": { "key_code": "f7" },
                            "to": [{ "consumer_key_code": "play_or_pause" }]
                        },
                        {
                            "from": { "key_code": "f8" },
                            "to": [{ "key_code": "mission_control" }]
                        },
                        {
                            "from": { "key_code": "f9" },
                            "to": [{ "consumer_key_code": "al_email_reader" }]
                        },
                        {
                            "from": { "key_code": "f10" },
                            "to": [{ "consumer_key_code": "al_local_machine_browser" }]
                        },
                        {
                            "from": { "key_code": "f11" },
                            "to": [{ "consumer_key_code": "al_text_editor" }]
                        },
                        {
                            "from": { "key_code": "f12" },
                            "to": [{ "consumer_key_code": "al_calculator" }]
                        }
                    ],
                    "identifiers": {
                        "is_keyboard": true,
                        "product_id": 73,
                        "vendor_id": 9610
                    },
                    "simple_modifications": [
                        {
                            "from": { "key_code": "caps_lock" },
                            "to": [{ "key_code": "escape" }]
                        },
                        {
                            "from": { "key_code": "escape" },
                            "to": [{ "key_code": "caps_lock" }]
                        },
                        {
                            "from": { "key_code": "left_option" },
                            "to": [{ "key_code": "left_command" }]
                        },
                        {
                            "from": { "key_code": "left_control" },
                            "to": [{ "apple_vendor_top_case_key_code": "keyboard_fn" }]
                        }
                    ]
                }
            ],
            "fn_function_keys": [
                {
                    "from": { "key_code": "f3" },
                    "to": [{ "key_code": "f3" }]
                },
                {
                    "from": { "key_code": "f4" },
                    "to": [{ "pointing_button": "button2" }]
                },
                {
                    "from": { "key_code": "f5" },
                    "to": [{ "consumer_key_code": "al_consumer_control_configuration" }]
                },
                {
                    "from": { "key_code": "f6" },
                    "to": [{ "pointing_button": "button2" }]
                }
            ],
            "name": "Default profile",
            "selected": true,
            "virtual_hid_keyboard": { "keyboard_type_v2": "ansi" }
        }
    ]
}